agent_chaos/__init__.py
agent_chaos/__main__.py
agent_chaos/cli.py
agent_chaos/fuzz.py
agent_chaos/py.typed
agent_chaos/chaos/__init__.py
agent_chaos/chaos/base.py
agent_chaos/chaos/builder.py
agent_chaos/chaos/context.py
agent_chaos/chaos/history.py
agent_chaos/chaos/llm.py
agent_chaos/chaos/stream.py
agent_chaos/chaos/tool.py
agent_chaos/chaos/user.py
agent_chaos/core/__init__.py
agent_chaos/core/context.py
agent_chaos/core/injector.py
agent_chaos/core/metrics.py
agent_chaos/event/__init__.py
agent_chaos/event/jsonl.py
agent_chaos/integrations/__init__.py
agent_chaos/integrations/deepeval.py
agent_chaos/patch/__init__.py
agent_chaos/patch/base.py
agent_chaos/patch/discovery.py
agent_chaos/patch/patcher.py
agent_chaos/patch/providers/__init__.py
agent_chaos/patch/providers/anthropic.py
agent_chaos/patch/providers/gemini.py
agent_chaos/patch/providers/openai.py
agent_chaos/scenario/__init__.py
agent_chaos/scenario/assertions.py
agent_chaos/scenario/loader.py
agent_chaos/scenario/model.py
agent_chaos/scenario/report.py
agent_chaos/scenario/runner.py
agent_chaos/stream/__init__.py
agent_chaos/stream/anthropic.py
agent_chaos/stream/gemini.py
agent_chaos/stream/openai.py
agent_chaos/ui/__init__.py
agent_chaos/ui/events.py
agent_chaos/ui/server.py
agent_chaos/ui/static/app.js
agent_chaos/ui/static/favicon.svg
agent_chaos/ui/static/index.html
agent_chaos/ui/static/styles.css
agent_chaos-0.1.2.dist-info/METADATA
agent_chaos-0.1.2.dist-info/WHEEL
agent_chaos-0.1.2.dist-info/entry_points.txt
agent_chaos-0.1.2.dist-info/licenses/LICENSE
agent_chaos-0.1.2.dist-info/RECORD
