Metadata-Version: 2.4
Name: agent-chaos
Version: 0.1.2
Summary: Chaos Engineering for AI Agents
Author-email: Deepankar Mahapatro <deepankarmahapatro@gmail.com>
License-File: LICENSE
Requires-Python: >=3.12
Requires-Dist: fastapi>=0.115
Requires-Dist: httpx>=0.27
Requires-Dist: uvicorn>=0.32
Requires-Dist: websockets>=14.0
Provides-Extra: all
Requires-Dist: anthropic>=0.75.0; extra == 'all'
Requires-Dist: google-genai>=1.40.0; extra == 'all'
Requires-Dist: openai>=1.0.0; extra == 'all'
Provides-Extra: anthropic
Requires-Dist: anthropic>=0.75.0; extra == 'anthropic'
Provides-Extra: gemini
Requires-Dist: google-genai>=1.40.0; extra == 'gemini'
Provides-Extra: openai
Requires-Dist: openai>=1.0.0; extra == 'openai'
